src/__init__.py
src/gen_args.py
src/geodetic_to_grid.py
elpt-0.1.0.dist-info/METADATA
elpt-0.1.0.dist-info/WHEEL
elpt-0.1.0.dist-info/top_level.txt
elpt-0.1.0.dist-info/RECORD
