Metadata-Version: 2.1
Name: elpt
Version: 0.1.0
Requires-Dist: numpy
